ts_bolt/__init__.py
ts_bolt/cli.py
ts_bolt/datamodules/__init__.py
ts_bolt/datamodules/gluonts.py
ts_bolt/datamodules/pandas.py
ts_bolt/datasets/__init__.py
ts_bolt/datasets/collections.py
ts_bolt/datasets/downloaders/__init__.py
ts_bolt/datasets/downloaders/base.py
ts_bolt/datasets/downloaders/ecb_exchange_rate.py
ts_bolt/evaluation/__init__.py
ts_bolt/evaluation/evaluator.py
ts_bolt/naive_forecasters/__init__.py
ts_bolt/naive_forecasters/last_observation.py
ts_bolt-0.0.7.dist-info/LICENSE
ts_bolt-0.0.7.dist-info/METADATA
ts_bolt-0.0.7.dist-info/WHEEL
ts_bolt-0.0.7.dist-info/entry_points.txt
ts_bolt-0.0.7.dist-info/RECORD
