Metadata-Version: 2.3
Name: ts_bolt
Version: 0.0.7
Summary: The Lightning Bolt for Time Series Data and Models
License: MIT
Author: LM
Author-email: hi@leima.is
Requires-Python: >=3.10,<3.13
Classifier: License :: OSI Approved :: MIT License
Classifier: Programming Language :: Python :: 3
Classifier: Programming Language :: Python :: 3.10
Classifier: Programming Language :: Python :: 3.11
Classifier: Programming Language :: Python :: 3.12
Requires-Dist: click (>=8.1.3,<9.0.0)
Requires-Dist: cloudpathlib (>=0.16.0,<0.17.0)
Requires-Dist: lightning (>=2.1.0,<3.0.0)
Requires-Dist: loguru (>=0.7.2,<0.8.0)
Requires-Dist: multidict (>=6.0.5,<7.0.0)
Requires-Dist: pandas (>=2.1.1,<3.0.0)
Requires-Dist: pydantic (>=1.10.4,<2.0)
Requires-Dist: requests (>=2.28.2,<3.0.0)
Requires-Dist: scipy (>=1.11.3,<2.0.0)
Requires-Dist: strenum (>=0.4.9,<0.5.0)
Requires-Dist: torch (>=1.13.1)
